famegui/__init__.py
famegui/__main__.py
famegui/agent_controller.py
famegui/app.py
famegui/appworkingdir.py
famegui/colorpalette.py
famegui/database.sqlite3
famegui/maincontroller.py
famegui/mainwindow.py
famegui/path_config.py
famegui/path_resolver.py
famegui/resources_rc.py
famegui/scenario_graph_view.py
famegui/scenario_helper.py
famegui/time_utils.py
famegui/usersettings.py
famegui/utils.py
famegui/config/__init__.py
famegui/config/config.py
famegui/config/contract_consts.py
famegui/config/keymap_defaults.py
famegui/config/runtime_consts.py
famegui/config/static_ui_components.py
famegui/config/static_ui_descriptions.py
famegui/config/style_config.py
famegui/data/database.sqlite3
famegui/data/schema-example.yaml
famegui/data_manager/__init__.py
famegui/data_manager/loader.py
famegui/data_manager/string_set_manager.py
famegui/database/__init__.py
famegui/database/database.sqlite3
famegui/database/db_management.py
famegui/database/tables.py
famegui/database/db_loader/__init__.py
famegui/database/db_loader/db_manager.py
famegui/database/dbms/__init__.py
famegui/database/dbms/agent_db_manger.py
famegui/database/dbms/main.py
famegui/database/prebuild_queries/__init__.py
famegui/database/prebuild_queries/agent_colors_queries.py
famegui/database/prebuild_queries/consts_from_settings.py
famegui/database/prebuild_queries/general.py
famegui/database/prebuild_queries/interval_presets.py
famegui/database/settings_db/__init__.py
famegui/database/settings_db/init_db.py
famegui/database/settings_db/tables.py
famegui/dialogs/__init__.py
famegui/dialogs/ask_for_agent_deletion_dialog.py
famegui/dialogs/delete_agent_dialog.py
famegui/dialogs/dialog_new_multi_dialog.py
famegui/dialogs/dialog_newagent.py
famegui/dialogs/dialog_newcontract.py
famegui/dialogs/dialog_scenario_properties.py
famegui/dialogs/edit_agent_dialog.py
famegui/dialogs/edit_contract_dialog.py
famegui/dialogs/famegui_config_presets_dialog.py
famegui/dialogs/multi_edit_contract_dialog.py
famegui-0.9.0.dist-info/LICENSE
famegui-0.9.0.dist-info/METADATA
famegui-0.9.0.dist-info/WHEEL
famegui-0.9.0.dist-info/entry_points.txt
famegui-0.9.0.dist-info/top_level.txt
famegui-0.9.0.dist-info/RECORD
