Metadata-Version: 2.1
Name: famegui
Version: 0.9.0
Summary: Graphical user interface to the FAME modelling framework
Home-page: https://gitlab.com/fame-framework/FAME-Gui
Download-URL: https://gitlab.com/fame-framework/FAME-Gui/-/archive/v0.9.0/FAME-Gui-v0.9.0.tar.gz
Author: Aurélien Regat-Barrel, Simon Wischnevetski
Author-email: fame@dlr.de
License: Apache License 2.0
Keywords: FAME,agent-based modelling
Classifier: Development Status :: 4 - Beta
Classifier: Intended Audience :: Science/Research
Classifier: Topic :: Scientific/Engineering :: Visualization
Classifier: License :: OSI Approved :: Apache Software License
Classifier: Programming Language :: Python :: 3.9
Classifier: Programming Language :: Python :: 3.10
Classifier: Programming Language :: Python :: 3.11
Requires-Python: >=3.9
License-File: LICENSE
Requires-Dist: coloredlogs
Requires-Dist: fameio >=3.0
Requires-Dist: python-igraph
Requires-Dist: pyyaml
Requires-Dist: ipython
Requires-Dist: PySide6
Requires-Dist: SQLAlchemy >=1.4.44
Requires-Dist: pytest ==8.3.4
Requires-Dist: matplotlib
Requires-Dist: ujson
Requires-Dist: icecream
